flex_docker/__init__.py
flex_docker/__main__.py
flex_docker_compose/__init__.py
flex_docker_compose/__main__.py
flex_docker_compose/etc/__init__.py
flex_docker_compose/etc/config.py
flex_docker_compose/shell_proxy.py
flex_docker-0.2.2.dist-info/LICENSE
flex_docker-0.2.2.dist-info/METADATA
flex_docker-0.2.2.dist-info/WHEEL
flex_docker-0.2.2.dist-info/entry_points.txt
flex_docker-0.2.2.dist-info/RECORD
