Metadata-Version: 2.1
Name: flex-docker
Version: 0.2.2
Summary: Flex docker is a utility wrapper around docker and docker-compose commands providing defaults values for projects
Home-page: https://github.com/a42ss/flex-docker
License: MIT
Keywords: docker-compose,docker,flex-cli,flex-docker,flex-docker-compose
Author: George Babarus
Author-email: george.babarus@gmail.com
Requires-Python: >=3.8,<4.0
Classifier: License :: OSI Approved :: MIT License
Classifier: Programming Language :: Python :: 3
Classifier: Programming Language :: Python :: 3.8
Classifier: Programming Language :: Python :: 3.9
Classifier: Programming Language :: Python :: 3.10
Classifier: Programming Language :: Python :: 3.11
Requires-Dist: flex-cli (>=0.3,<0.4)
Project-URL: Repository, https://github.com/a42ss/flex-docker
